1to10pgms/1to5.py
1to10pgms/6to10.py
1to10pgms/__init__.py
codesignal1to10-0.0.1.dist-info/DESCRIPTION.rst
codesignal1to10-0.0.1.dist-info/METADATA
codesignal1to10-0.0.1.dist-info/RECORD
codesignal1to10-0.0.1.dist-info/WHEEL
codesignal1to10-0.0.1.dist-info/metadata.json
codesignal1to10-0.0.1.dist-info/top_level.txt
codesignal_pgms/__init__.py
codesignal_pgms/one_to_five.py
codesignal_pgms/siz_to_ten.py
pgms/1to5.py
pgms/6to10.py
pgms/__init__.py
pgms/one_to_five.py
pgms/siz_to_ten.py
