Metadata-Version: 2.0
Name: codesignal1to10
Version: 0.0.1
Summary: Codesignal programs 1 to 10
Home-page: UNKNOWN
Author: Sukumar
Author-email: sukurcf@gmail.com
License: UNKNOWN
Platform: UNKNOWN
Classifier: Programming Language :: Python :: 3
Classifier: License :: OSI Approved :: MIT License
Classifier: Operating System :: OS Independent
Requires-Python: >=3.7
